epidemia/__init__.py
epidemia/epidemia.py
epidemia/epidemic.py
epidemia/ivorra.py
epidemia/mcmc.py
epidemia/models.py
epidemia/perf.py
epidemia/webapp.py
epidemia-0.0.3.dist-info/LICENSE
epidemia-0.0.3.dist-info/METADATA
epidemia-0.0.3.dist-info/WHEEL
epidemia-0.0.3.dist-info/top_level.txt
epidemia-0.0.3.dist-info/RECORD
