Metadata-Version: 2.1
Name: epidemia
Version: 0.0.3
Summary: Modelling COVID-19 using SIR-like models
Home-page: https://github.com/COVID19-CMM/Epidemia
Author: Taco de Wolff
Author-email: tacodewolff@gmail.com
License: MIT
Keywords: epidemic,SIR,SEIR,COVID-19,corona,virus,compartmental
Platform: UNKNOWN
Requires-Python: >=3.6
Requires-Dist: numpy
Requires-Dist: pandas
Requires-Dist: matplotlib
Requires-Dist: scipy
Requires-Dist: scikit-optimize
Requires-Dist: pyswarms
Requires-Dist: pymc3
